LICENSE
MANIFEST.in
README.md
setup.py
tap_google_sheets/__init__.py
tap_google_sheets/client.py
tap_google_sheets/discover.py
tap_google_sheets/schema.py
tap_google_sheets/streams.py
tap_google_sheets/sync.py
tap_google_sheets/transform.py
tap_google_sheets.egg-info/PKG-INFO
tap_google_sheets.egg-info/SOURCES.txt
tap_google_sheets.egg-info/dependency_links.txt
tap_google_sheets.egg-info/entry_points.txt
tap_google_sheets.egg-info/requires.txt
tap_google_sheets.egg-info/top_level.txt
tap_google_sheets/schemas/file_metadata.json
tap_google_sheets/schemas/sheet_metadata.json
tap_google_sheets/schemas/sheets_loaded.json
tap_google_sheets/schemas/spreadsheet_metadata.json
tests/__init__.py
tests/base.py
tests/test_google_sheets_all_fields.py
tests/test_google_sheets_automatic_fields.py
tests/test_google_sheets_bookmarks.py
tests/test_google_sheets_datatypes.py
tests/test_google_sheets_discovery.py
tests/test_google_sheets_pagination.py