Metadata-Version: 2.1
Name: tap-google-sheets
Version: 3.1.2
Summary: Singer.io tap for extracting data from the Google Sheets v4 API
Author: jeff.huth@bytecode.io
Classifier: Programming Language :: Python :: 3 :: Only
License-File: LICENSE
Requires-Dist: backoff==2.2.1
Requires-Dist: requests==2.32.4
Requires-Dist: singer-python==6.0.1
Provides-Extra: test
Requires-Dist: pylint; extra == "test"
Requires-Dist: nose; extra == "test"
Provides-Extra: dev
Requires-Dist: ipdb; extra == "dev"
